dsa_buddy.py
dsa_buddy-3.0.7.dist-info/LICENSE.txt
dsa_buddy-3.0.7.dist-info/METADATA
dsa_buddy-3.0.7.dist-info/WHEEL
dsa_buddy-3.0.7.dist-info/top_level.txt
dsa_buddy-3.0.7.dist-info/RECORD
