Metadata-Version: 2.1
Name: dsa-buddy
Version: 3.0.7
Summary: dsa_buddy client for DSA preparation and code submission utlity
Home-page: UNKNOWN
Author: Botoservices
Author-email: botoservices@gmail.com
License: MIT
Keywords: dsa buddy coding python
Platform: UNKNOWN
Classifier: Development Status :: 3 - Alpha
Classifier: Intended Audience :: Developers
Classifier: License :: OSI Approved :: MIT License
Classifier: Programming Language :: Python :: 3
License-File: LICENSE.txt
Requires-Dist: requests
Requires-Dist: pwinput
